README.md
setup.py
bin/drophi
drophi/__init__.py
drophi/client.py
drophi/main.py
drophi/serializer.py
drophi.egg-info/PKG-INFO
drophi.egg-info/SOURCES.txt
drophi.egg-info/dependency_links.txt
drophi.egg-info/requires.txt
drophi.egg-info/top_level.txt
drophi/types/__init__.py
drophi/types/base.py
drophi/types/config.py
drophi/types/container.py
drophi/types/image.py
drophi/types/network.py
drophi/types/secret.py
drophi/types/service.py
drophi/types/volume.py