Metadata-Version: 1.0
Name: drophi
Version: 1.21
Summary: A client for interacting with docker daemon
Home-page: https://bitbucket.com/Authentise/drophi
Author: Authentise, Inc.
Author-email: engineering@authentise.com
License: UNKNOWN
Platform: UNKNOWN
